google_reader.py
google_reader-0.0.3.dist-info/METADATA
google_reader-0.0.3.dist-info/WHEEL
google_reader-0.0.3.dist-info/licenses/LICENSE
google_reader-0.0.3.dist-info/RECORD
