Metadata-Version: 2.4
Name: google-reader
Version: 0.0.3
Summary: Python client library for feed readers that utilize the Google Reader API
Project-URL: Homepage, https://github.com/miniflux/google-reader
Project-URL: Bug Reports, https://github.com/miniflux/google-reader/issues
Project-URL: Source, https://github.com/miniflux/google-reader
Author: Frédéric Guillot
License-Expression: MIT
License-File: LICENSE
Classifier: Intended Audience :: Developers
Classifier: License :: OSI Approved :: MIT License
Classifier: Operating System :: OS Independent
Classifier: Programming Language :: Python :: 3
Requires-Python: >=3.12
Requires-Dist: requests
